<?xml version="1.0" encoding="UTF-8" standalone="no" ?>
<Table>

  <TableId>234</TableId>

  <DeleteCode>0</DeleteCode>

  <Name>Plaintiff</Name>

  <DocName>PLAINTIFF</DocName>

  <Transaction>false</Transaction>

  <BasedOnCard>true</BasedOnCard>

  <OSUniqueId>159001</OSUniqueId>

  <Singleton>false</Singleton>

  <TableLayouts>
    <TableLayout>
      <Layout_LayoutId>404</Layout_LayoutId>
      <Layout_Title>Details</Layout_Title>
      <Table_TableId>234</Table_TableId>
      <ShownOnMatter>False</ShownOnMatter>
      <MatterType_MatterCategoryId>22</MatterType_MatterCategoryId>
      <MatterType_MatterTypeId/>
    </TableLayout>
    <TableLayout>
      <Layout_LayoutId>1396</Layout_LayoutId>
      <Layout_Title>Role</Layout_Title>
      <Table_TableId>234</Table_TableId>
      <ShownOnMatter>True</ShownOnMatter>
      <MatterType_MatterCategoryId>79</MatterType_MatterCategoryId>
      <MatterType_MatterTypeId>654</MatterType_MatterTypeId>
    </TableLayout>
    <TableLayout>
      <Layout_LayoutId>1396</Layout_LayoutId>
      <Layout_Title>Role</Layout_Title>
      <Table_TableId>234</Table_TableId>
      <ShownOnMatter>True</ShownOnMatter>
      <MatterType_MatterCategoryId>22</MatterType_MatterCategoryId>
      <MatterType_MatterTypeId>644</MatterType_MatterTypeId>
    </TableLayout>
    <TableLayout>
      <Layout_LayoutId>1396</Layout_LayoutId>
      <Layout_Title>Role</Layout_Title>
      <Table_TableId>234</Table_TableId>
      <ShownOnMatter>True</ShownOnMatter>
      <MatterType_MatterCategoryId>15</MatterType_MatterCategoryId>
      <MatterType_MatterTypeId>241</MatterType_MatterTypeId>
    </TableLayout>
    <TableLayout>
      <Layout_LayoutId>1396</Layout_LayoutId>
      <Layout_Title>Role</Layout_Title>
      <Table_TableId>234</Table_TableId>
      <ShownOnMatter>True</ShownOnMatter>
      <MatterType_MatterCategoryId>79</MatterType_MatterCategoryId>
      <MatterType_MatterTypeId>652</MatterType_MatterTypeId>
    </TableLayout>
    <TableLayout>
      <Layout_LayoutId>1396</Layout_LayoutId>
      <Layout_Title>Role</Layout_Title>
      <Table_TableId>234</Table_TableId>
      <ShownOnMatter>True</ShownOnMatter>
      <MatterType_MatterCategoryId>22</MatterType_MatterCategoryId>
      <MatterType_MatterTypeId>642</MatterType_MatterTypeId>
    </TableLayout>
    <TableLayout>
      <Layout_LayoutId>1396</Layout_LayoutId>
      <Layout_Title>Role</Layout_Title>
      <Table_TableId>234</Table_TableId>
      <ShownOnMatter>True</ShownOnMatter>
      <MatterType_MatterCategoryId>70</MatterType_MatterCategoryId>
      <MatterType_MatterTypeId>414</MatterType_MatterTypeId>
    </TableLayout>
    <TableLayout>
      <Layout_LayoutId>1396</Layout_LayoutId>
      <Layout_Title>Role</Layout_Title>
      <Table_TableId>234</Table_TableId>
      <ShownOnMatter>True</ShownOnMatter>
      <MatterType_MatterCategoryId>29</MatterType_MatterCategoryId>
      <MatterType_MatterTypeId>413</MatterType_MatterTypeId>
    </TableLayout>
    <TableLayout>
      <Layout_LayoutId>1396</Layout_LayoutId>
      <Layout_Title>Role</Layout_Title>
      <Table_TableId>234</Table_TableId>
      <ShownOnMatter>True</ShownOnMatter>
      <MatterType_MatterCategoryId>29</MatterType_MatterCategoryId>
      <MatterType_MatterTypeId>540</MatterType_MatterTypeId>
    </TableLayout>
    <TableLayout>
      <Layout_LayoutId>1396</Layout_LayoutId>
      <Layout_Title>Role</Layout_Title>
      <Table_TableId>234</Table_TableId>
      <ShownOnMatter>True</ShownOnMatter>
      <MatterType_MatterCategoryId>69</MatterType_MatterCategoryId>
      <MatterType_MatterTypeId>411</MatterType_MatterTypeId>
    </TableLayout>
    <TableLayout>
      <Layout_LayoutId>1396</Layout_LayoutId>
      <Layout_Title>Role</Layout_Title>
      <Table_TableId>234</Table_TableId>
      <ShownOnMatter>True</ShownOnMatter>
      <MatterType_MatterCategoryId>69</MatterType_MatterCategoryId>
      <MatterType_MatterTypeId>1161</MatterType_MatterTypeId>
    </TableLayout>
    <TableLayout>
      <Layout_LayoutId>1396</Layout_LayoutId>
      <Layout_Title>Role</Layout_Title>
      <Table_TableId>234</Table_TableId>
      <ShownOnMatter>True</ShownOnMatter>
      <MatterType_MatterCategoryId>69</MatterType_MatterCategoryId>
      <MatterType_MatterTypeId>820</MatterType_MatterTypeId>
    </TableLayout>
    <TableLayout>
      <Layout_LayoutId>1396</Layout_LayoutId>
      <Layout_Title>Role</Layout_Title>
      <Table_TableId>234</Table_TableId>
      <ShownOnMatter>True</ShownOnMatter>
      <MatterType_MatterCategoryId>69</MatterType_MatterCategoryId>
      <MatterType_MatterTypeId>819</MatterType_MatterTypeId>
    </TableLayout>
    <TableLayout>
      <Layout_LayoutId>1396</Layout_LayoutId>
      <Layout_Title>Role</Layout_Title>
      <Table_TableId>234</Table_TableId>
      <ShownOnMatter>True</ShownOnMatter>
      <MatterType_MatterCategoryId>69</MatterType_MatterCategoryId>
      <MatterType_MatterTypeId>818</MatterType_MatterTypeId>
    </TableLayout>
    <TableLayout>
      <Layout_LayoutId>1396</Layout_LayoutId>
      <Layout_Title>Role</Layout_Title>
      <Table_TableId>234</Table_TableId>
      <ShownOnMatter>True</ShownOnMatter>
      <MatterType_MatterCategoryId>69</MatterType_MatterCategoryId>
      <MatterType_MatterTypeId>817</MatterType_MatterTypeId>
    </TableLayout>
    <TableLayout>
      <Layout_LayoutId>1396</Layout_LayoutId>
      <Layout_Title>Role</Layout_Title>
      <Table_TableId>234</Table_TableId>
      <ShownOnMatter>True</ShownOnMatter>
      <MatterType_MatterCategoryId>69</MatterType_MatterCategoryId>
      <MatterType_MatterTypeId>816</MatterType_MatterTypeId>
    </TableLayout>
    <TableLayout>
      <Layout_LayoutId>1441</Layout_LayoutId>
      <Layout_Title>Role</Layout_Title>
      <Table_TableId>234</Table_TableId>
      <ShownOnMatter>True</ShownOnMatter>
      <MatterType_MatterCategoryId>22</MatterType_MatterCategoryId>
      <MatterType_MatterTypeId>508</MatterType_MatterTypeId>
    </TableLayout>
    <TableLayout>
      <Layout_LayoutId>1441</Layout_LayoutId>
      <Layout_Title>Role</Layout_Title>
      <Table_TableId>234</Table_TableId>
      <ShownOnMatter>True</ShownOnMatter>
      <MatterType_MatterCategoryId>22</MatterType_MatterCategoryId>
      <MatterType_MatterTypeId>146</MatterType_MatterTypeId>
    </TableLayout>
    <TableLayout>
      <Layout_LayoutId>1441</Layout_LayoutId>
      <Layout_Title>Role</Layout_Title>
      <Table_TableId>234</Table_TableId>
      <ShownOnMatter>True</ShownOnMatter>
      <MatterType_MatterCategoryId>22</MatterType_MatterCategoryId>
      <MatterType_MatterTypeId>234</MatterType_MatterTypeId>
    </TableLayout>
    <TableLayout>
      <Layout_LayoutId>1441</Layout_LayoutId>
      <Layout_Title>Role</Layout_Title>
      <Table_TableId>234</Table_TableId>
      <ShownOnMatter>True</ShownOnMatter>
      <MatterType_MatterCategoryId>22</MatterType_MatterCategoryId>
      <MatterType_MatterTypeId>232</MatterType_MatterTypeId>
    </TableLayout>
    <TableLayout>
      <Layout_LayoutId>1441</Layout_LayoutId>
      <Layout_Title>Role</Layout_Title>
      <Table_TableId>234</Table_TableId>
      <ShownOnMatter>True</ShownOnMatter>
      <MatterType_MatterCategoryId>22</MatterType_MatterCategoryId>
      <MatterType_MatterTypeId>366</MatterType_MatterTypeId>
    </TableLayout>
    <TableLayout>
      <Layout_LayoutId>1441</Layout_LayoutId>
      <Layout_Title>Role</Layout_Title>
      <Table_TableId>234</Table_TableId>
      <ShownOnMatter>True</ShownOnMatter>
      <MatterType_MatterCategoryId>22</MatterType_MatterCategoryId>
      <MatterType_MatterTypeId>98</MatterType_MatterTypeId>
    </TableLayout>
    <TableLayout>
      <Layout_LayoutId>1441</Layout_LayoutId>
      <Layout_Title>Role</Layout_Title>
      <Table_TableId>234</Table_TableId>
      <ShownOnMatter>True</ShownOnMatter>
      <MatterType_MatterCategoryId>22</MatterType_MatterCategoryId>
      <MatterType_MatterTypeId>149</MatterType_MatterTypeId>
    </TableLayout>
    <TableLayout>
      <Layout_LayoutId>1441</Layout_LayoutId>
      <Layout_Title>Role</Layout_Title>
      <Table_TableId>234</Table_TableId>
      <ShownOnMatter>True</ShownOnMatter>
      <MatterType_MatterCategoryId>22</MatterType_MatterCategoryId>
      <MatterType_MatterTypeId>170</MatterType_MatterTypeId>
    </TableLayout>
    <TableLayout>
      <Layout_LayoutId>1441</Layout_LayoutId>
      <Layout_Title>Role</Layout_Title>
      <Table_TableId>234</Table_TableId>
      <ShownOnMatter>True</ShownOnMatter>
      <MatterType_MatterCategoryId>22</MatterType_MatterCategoryId>
      <MatterType_MatterTypeId>147</MatterType_MatterTypeId>
    </TableLayout>
    <TableLayout>
      <Layout_LayoutId>1441</Layout_LayoutId>
      <Layout_Title>Role</Layout_Title>
      <Table_TableId>234</Table_TableId>
      <ShownOnMatter>True</ShownOnMatter>
      <MatterType_MatterCategoryId>22</MatterType_MatterCategoryId>
      <MatterType_MatterTypeId>372</MatterType_MatterTypeId>
    </TableLayout>
    <TableLayout>
      <Layout_LayoutId>1441</Layout_LayoutId>
      <Layout_Title>Role</Layout_Title>
      <Table_TableId>234</Table_TableId>
      <ShownOnMatter>True</ShownOnMatter>
      <MatterType_MatterCategoryId>69</MatterType_MatterCategoryId>
      <MatterType_MatterTypeId>346</MatterType_MatterTypeId>
    </TableLayout>
    <TableLayout>
      <Layout_LayoutId>1441</Layout_LayoutId>
      <Layout_Title>Role</Layout_Title>
      <Table_TableId>234</Table_TableId>
      <ShownOnMatter>True</ShownOnMatter>
      <MatterType_MatterCategoryId>70</MatterType_MatterCategoryId>
      <MatterType_MatterTypeId>124</MatterType_MatterTypeId>
    </TableLayout>
    <TableLayout>
      <Layout_LayoutId>1441</Layout_LayoutId>
      <Layout_Title>Role</Layout_Title>
      <Table_TableId>234</Table_TableId>
      <ShownOnMatter>True</ShownOnMatter>
      <MatterType_MatterCategoryId>29</MatterType_MatterCategoryId>
      <MatterType_MatterTypeId>123</MatterType_MatterTypeId>
    </TableLayout>
    <TableLayout>
      <Layout_LayoutId>1441</Layout_LayoutId>
      <Layout_Title>Role</Layout_Title>
      <Table_TableId>234</Table_TableId>
      <ShownOnMatter>True</ShownOnMatter>
      <MatterType_MatterCategoryId>29</MatterType_MatterCategoryId>
      <MatterType_MatterTypeId>343</MatterType_MatterTypeId>
    </TableLayout>
    <TableLayout>
      <Layout_LayoutId>1441</Layout_LayoutId>
      <Layout_Title>Role</Layout_Title>
      <Table_TableId>234</Table_TableId>
      <ShownOnMatter>True</ShownOnMatter>
      <MatterType_MatterCategoryId>15</MatterType_MatterCategoryId>
      <MatterType_MatterTypeId>53</MatterType_MatterTypeId>
    </TableLayout>
    <TableLayout>
      <Layout_LayoutId>1441</Layout_LayoutId>
      <Layout_Title>Role</Layout_Title>
      <Table_TableId>234</Table_TableId>
      <ShownOnMatter>True</ShownOnMatter>
      <MatterType_MatterCategoryId>69</MatterType_MatterCategoryId>
      <MatterType_MatterTypeId>125</MatterType_MatterTypeId>
    </TableLayout>
    <TableLayout>
      <Layout_LayoutId>1441</Layout_LayoutId>
      <Layout_Title>Role</Layout_Title>
      <Table_TableId>234</Table_TableId>
      <ShownOnMatter>True</ShownOnMatter>
      <MatterType_MatterCategoryId>70</MatterType_MatterCategoryId>
      <MatterType_MatterTypeId>634</MatterType_MatterTypeId>
    </TableLayout>
    <TableLayout>
      <Layout_LayoutId>1441</Layout_LayoutId>
      <Layout_Title>Role</Layout_Title>
      <Table_TableId>234</Table_TableId>
      <ShownOnMatter>True</ShownOnMatter>
      <MatterType_MatterCategoryId>29</MatterType_MatterCategoryId>
      <MatterType_MatterTypeId>507</MatterType_MatterTypeId>
    </TableLayout>
    <TableLayout>
      <Layout_LayoutId>1441</Layout_LayoutId>
      <Layout_Title>Role</Layout_Title>
      <Table_TableId>234</Table_TableId>
      <ShownOnMatter>True</ShownOnMatter>
      <MatterType_MatterCategoryId>29</MatterType_MatterCategoryId>
      <MatterType_MatterTypeId>539</MatterType_MatterTypeId>
    </TableLayout>
    <TableLayout>
      <Layout_LayoutId>1441</Layout_LayoutId>
      <Layout_Title>Role</Layout_Title>
      <Table_TableId>234</Table_TableId>
      <ShownOnMatter>True</ShownOnMatter>
      <MatterType_MatterCategoryId>15</MatterType_MatterCategoryId>
      <MatterType_MatterTypeId>491</MatterType_MatterTypeId>
    </TableLayout>
    <TableLayout>
      <Layout_LayoutId>1441</Layout_LayoutId>
      <Layout_Title>Role</Layout_Title>
      <Table_TableId>234</Table_TableId>
      <ShownOnMatter>True</ShownOnMatter>
      <MatterType_MatterCategoryId>69</MatterType_MatterCategoryId>
      <MatterType_MatterTypeId>488</MatterType_MatterTypeId>
    </TableLayout>
  </TableLayouts>

</Table>
