<?xml version="1.0" encoding="UTF-8" standalone="no" ?>
<Table>

  <TableId>942</TableId>

  <DeleteCode>0</DeleteCode>

  <Name>CARS Forms</Name>

  <DocName>CARS_FORMS</DocName>

  <Transaction>false</Transaction>

  <BasedOnCard>false</BasedOnCard>

  <OSUniqueId>831001</OSUniqueId>

  <Singleton>false</Singleton>

  <TableLayouts>
    <TableLayout>
      <Layout_LayoutId>1387</Layout_LayoutId>
      <Layout_Title>CARS Form Details</Layout_Title>
      <Table_TableId>942</Table_TableId>
      <ShownOnMatter>False</ShownOnMatter>
      <MatterType_MatterCategoryId/>
      <MatterType_MatterTypeId/>
    </TableLayout>
  </TableLayouts>

</Table>
